[
  {
    "id": "rec0pRjN3vEi1Jlkw",
    "createdTime": "2024-08-08T18:39:19.000Z",
    "fields": {
      "Date (GMT)": "2024-08-08 16:40:50",
      "Job Link": "https://dashboard.browse.ai/teams/personal/robots/6b1f28ae-4557-4569-a58b-60e919d89150/history/63234645-67f3-43c9-b647-7562bd5baec3",
      "Origin URL": "https://taplio.com/lookup/alicjasmin",
      "Profile Links Limit": 100,
      "LinkedIn Posts Limit": 100,
      "followers": 234,
      "sd": 20,
      "engagements": 78,
      "likes": 45
    }
  },
  {
    "id": "rec0ySpsU1cLcUa05",
    "createdTime": "2024-08-08T18:39:19.000Z",
    "fields": {
      "Date (GMT)": "2024-08-08 16:53:18",
      "Job Link": "https://dashboard.browse.ai/teams/personal/robots/6b1f28ae-4557-4569-a58b-60e919d89150/history/190e496c-fb3d-45a0-849d-af5981b4fa9b",
      "Origin URL": "https://taplio.com/lookup/eczachly",
      "Profile Links Limit": 100,
      "LinkedIn Posts Limit": 100,
      "followers": 380,
      "sd": 20,
      "engagements": 24,
      "likes": 22
    }
  },
  {
    "id": "rec18jPl8UJ9j6Q4z",
    "createdTime": "2024-08-08T18:39:19.000Z",
    "fields": {
      "Date (GMT)": "2024-08-08 16:52:01",
      "Job Link": "https://dashboard.browse.ai/teams/personal/robots/6b1f28ae-4557-4569-a58b-60e919d89150/history/08a78326-df60-4383-8ba9-20fc869d5d8e",
      "Origin URL": "https://taplio.com/lookup/teresatorres",
      "Profile Links Limit": 100,
      "LinkedIn Posts Limit": 100,
      "followers": 104,
      "sd": 20,
      "engagements": 3,
      "likes": 3
    }
  },
  {
    "id": "rec2BaJEzXeCK1n6l",
    "createdTime": "2024-08-08T18:39:19.000Z",
    "fields": {
      "Date (GMT)": "2024-08-08 16:45:38",
      "Job Link": "https://dashboard.browse.ai/teams/personal/robots/6b1f28ae-4557-4569-a58b-60e919d89150/history/b328fe43-f693-4310-9597-25b1e0f563b5",
      "Origin URL": "https://taplio.com/lookup/marcuschanmba",
      "Profile Links Limit": 100,
      "LinkedIn Posts Limit": 100,
      "followers": 81,
      "sd": 20,
      "engagements": 3,
      "likes": 1
    }
  },
  {
    "id": "rec46xrbsb28StL61",
    "createdTime": "2024-08-08T18:39:19.000Z",
    "fields": {
      "Date (GMT)": "2024-08-08 16:52:03",
      "Job Link": "https://dashboard.browse.ai/teams/personal/robots/6b1f28ae-4557-4569-a58b-60e919d89150/history/6577add9-9bb6-4bd8-aeec-68ac8f72a2f7",
      "Origin URL": "https://taplio.com/lookup/ruben-hassid",
      "Profile Links Limit": 100,
      "LinkedIn Posts Limit": 100,
      "followers": 390,
      "sd": 20,
      "engagements": 36,
      "likes": 23
    }
  },
  {
    "id": "rec4QQdXwqG3ehBlC",
    "createdTime": "2024-08-08T18:39:19.000Z",
    "fields": {
      "Date (GMT)": "2024-08-08 16:40:05",
      "Job Link": "https://dashboard.browse.ai/teams/personal/robots/6b1f28ae-4557-4569-a58b-60e919d89150/history/425b0e4e-93dd-440a-a4c2-4ee47522277c",
      "Origin URL": "https://taplio.com/lookup/youssefkoutari",
      "Profile Links Limit": 100,
      "LinkedIn Posts Limit": 100,
      "followers": 468,
      "sd": 20,
      "engagements": 82,
      "likes": 71
    }
  },
  {
    "id": "rec5Xnr2lkQs3ezHc",
    "createdTime": "2024-08-08T18:39:19.000Z",
    "fields": {
      "Date (GMT)": "2024-08-08 16:57:34",
      "Job Link": "https://dashboard.browse.ai/teams/personal/robots/6b1f28ae-4557-4569-a58b-60e919d89150/history/f5f4ca03-3633-4dc6-9dd5-a479458a04a5",
      "Origin URL": "https://taplio.com/lookup/scottleese",
      "Profile Links Limit": 100,
      "LinkedIn Posts Limit": 100,
      "followers": 112,
      "sd": 20,
      "engagements": 7,
      "likes": 5
    }
  },
  {
    "id": "rec5zTiRxFPOJxjsF",
    "createdTime": "2024-08-08T18:39:19.000Z",
    "fields": {
      "Date (GMT)": "2024-08-08 17:00:17",
      "Job Link": "https://dashboard.browse.ai/teams/personal/robots/6b1f28ae-4557-4569-a58b-60e919d89150/history/13345625-d80a-4485-8848-acb01a5780f8",
      "Origin URL": "https://taplio.com/lookup/jermainelmurray",
      "Profile Links Limit": 100,
      "LinkedIn Posts Limit": 100,
      "followers": 89,
      "sd": 20,
      "engagements": 18,
      "likes": 16
    }
  },
  {
    "id": "rec7FgxKhmQ6XawYG",
    "createdTime": "2024-08-08T18:39:19.000Z",
    "fields": {
      "Date (GMT)": "2024-08-08 17:00:18",
      "Job Link": "https://dashboard.browse.ai/teams/personal/robots/6b1f28ae-4557-4569-a58b-60e919d89150/history/a83154f1-1bce-4538-8ed1-900a05196dff",
      "Origin URL": "https://taplio.com/lookup/sherricarpineto",
      "Profile Links Limit": 100,
      "LinkedIn Posts Limit": 100,
      "followers": 110,
      "sd": 20,
      "engagements": 46,
      "likes": 41
    }
  },
  {
    "id": "rec7nxaN61zuHc0KO",
    "createdTime": "2024-08-08T18:39:19.000Z",
    "fields": {
      "Date (GMT)": "2024-08-08 16:59:50",
      "Job Link": "https://dashboard.browse.ai/teams/personal/robots/6b1f28ae-4557-4569-a58b-60e919d89150/history/3a48a0f5-09f9-414f-a532-17510fc22c27",
      "Origin URL": "https://taplio.com/lookup/richardjamesmoore",
      "Profile Links Limit": 100,
      "LinkedIn Posts Limit": 100,
      "followers": 90,
      "sd": 19,
      "engagements": 5,
      "likes": 3
    }
  },
  {
    "id": "rec7qg9PoqQXwHBCk",
    "createdTime": "2024-08-08T18:39:19.000Z",
    "fields": {
      "Date (GMT)": "2024-08-08 17:04:47",
      "Job Link": "https://dashboard.browse.ai/teams/personal/robots/6b1f28ae-4557-4569-a58b-60e919d89150/history/b3533b36-fdeb-4273-9d9f-8863fb1ddb58",
      "Origin URL": "https://taplio.com/lookup/daniel-abrahams",
      "Profile Links Limit": 100,
      "LinkedIn Posts Limit": 100,
      "followers": 1,
      "sd": 20,
      "engagements": 263,
      "likes": 232
    }
  },
  {
    "id": "rec8IAFYy99EZUkIj",
    "createdTime": "2024-08-08T18:39:19.000Z",
    "fields": {
      "Date (GMT)": "2024-08-08 16:38:54",
      "Job Link": "https://dashboard.browse.ai/teams/personal/robots/6b1f28ae-4557-4569-a58b-60e919d89150/history/3fda73f4-ab29-4d87-817c-05e4956dc79c",
      "Origin URL": "https://taplio.com/lookup/danfounder",
      "Profile Links Limit": 100,
      "LinkedIn Posts Limit": 100,
      "followers": 332,
      "sd": 20,
      "engagements": 44,
      "likes": 39
    }
  },
  {
    "id": "rec8asbPFdVylfqXh",
    "createdTime": "2024-08-08T18:39:19.000Z",
    "fields": {
      "Date (GMT)": "2024-08-08 17:00:10",
      "Job Link": "https://dashboard.browse.ai/teams/personal/robots/6b1f28ae-4557-4569-a58b-60e919d89150/history/8611b246-eded-4136-905c-a1701754940a",
      "Origin URL": "https://taplio.com/lookup/danieldisney",
      "Profile Links Limit": 100,
      "LinkedIn Posts Limit": 100,
      "followers": 132,
      "sd": 20,
      "engagements": 17,
      "likes": 15
    }
  },
  {
    "id": "rec8lQgLvyd3NiKeB",
    "createdTime": "2024-08-08T18:39:19.000Z",
    "fields": {
      "Date (GMT)": "2024-08-08 16:42:46",
      "Job Link": "https://dashboard.browse.ai/teams/personal/robots/6b1f28ae-4557-4569-a58b-60e919d89150/history/3dc9b141-0f17-4b09-bed0-1b2782b8dedc",
      "Origin URL": "https://taplio.com/lookup/grantcardone",
      "Profile Links Limit": 100,
      "LinkedIn Posts Limit": 100,
      "followers": 604,
      "sd": 20,
      "engagements": 18,
      "likes": 16
    }
  },
  {
    "id": "rec9VvepGUY9mbm2T",
    "createdTime": "2024-08-08T18:39:19.000Z",
    "fields": {
      "Date (GMT)": "2024-08-08 16:40:52",
      "Job Link": "https://dashboard.browse.ai/teams/personal/robots/6b1f28ae-4557-4569-a58b-60e919d89150/history/6e62bb61-86ac-46e5-8992-696aade0e784",
      "Origin URL": "https://taplio.com/lookup/jousefmurad",
      "Profile Links Limit": 100,
      "LinkedIn Posts Limit": 100,
      "followers": 160,
      "sd": 20,
      "engagements": 23,
      "likes": 22
    }
  },
  {
    "id": "recBAaNqc7M1X3Wc0",
    "createdTime": "2024-08-08T18:39:19.000Z",
    "fields": {
      "Date (GMT)": "2024-08-08 16:48:48",
      "Job Link": "https://dashboard.browse.ai/teams/personal/robots/6b1f28ae-4557-4569-a58b-60e919d89150/history/bdf8cd3c-83e0-4345-b296-645910e63886",
      "Origin URL": "https://taplio.com/lookup/alexxubyte",
      "Profile Links Limit": 100,
      "LinkedIn Posts Limit": 100,
      "followers": 811,
      "sd": 20,
      "engagements": 77,
      "likes": 68
    }
  },
  {
    "id": "recBM1etHHDX78Kb3",
    "createdTime": "2024-08-08T18:39:19.000Z",
    "fields": {
      "Date (GMT)": "2024-08-08 16:49:31",
      "Job Link": "https://dashboard.browse.ai/teams/personal/robots/6b1f28ae-4557-4569-a58b-60e919d89150/history/c86ce3a6-44d2-4130-9884-4e6edc086aa8",
      "Origin URL": "https://taplio.com/lookup/ndubuisi-ekekwe-36068210",
      "Profile Links Limit": 100,
      "LinkedIn Posts Limit": 100,
      "followers": 188,
      "sd": 20,
      "engagements": 9,
      "likes": 6
    }
  },
  {
    "id": "recCURlqlWFT8D3t3",
    "createdTime": "2024-08-08T18:39:19.000Z",
    "fields": {
      "Date (GMT)": "2024-08-08 16:37:41",
      "Job Link": "https://dashboard.browse.ai/teams/personal/robots/6b1f28ae-4557-4569-a58b-60e919d89150/history/024e045d-e425-47ef-898e-c4f0ef1905d8",
      "Origin URL": "https://taplio.com/lookup/laraacostar",
      "Profile Links Limit": 100,
      "LinkedIn Posts Limit": 100,
      "followers": 163,
      "sd": 20,
      "engagements": 50,
      "likes": 31
    }
  },
  {
    "id": "recCyYUtii8jucgid",
    "createdTime": "2024-08-08T18:39:19.000Z",
    "fields": {
      "Date (GMT)": "2024-08-08 16:58:51",
      "Job Link": "https://dashboard.browse.ai/teams/personal/robots/6b1f28ae-4557-4569-a58b-60e919d89150/history/11cf3406-a3b2-4d92-b042-c4d6d1552aed",
      "Origin URL": "https://taplio.com/lookup/pooja-jain-898253106",
      "Profile Links Limit": 100,
      "LinkedIn Posts Limit": 100,
      "followers": 128,
      "sd": 14,
      "engagements": 5,
      "likes": 4
    }
  },
  {
    "id": "recD0LMgZ1CM6ydH6",
    "createdTime": "2024-08-08T18:39:19.000Z",
    "fields": {
      "Date (GMT)": "2024-08-08 16:40:32",
      "Job Link": "https://dashboard.browse.ai/teams/personal/robots/6b1f28ae-4557-4569-a58b-60e919d89150/history/008cfd28-ae52-4e74-9912-94571a0cc8a9",
      "Origin URL": "https://taplio.com/lookup/thedankoe",
      "Profile Links Limit": 100,
      "LinkedIn Posts Limit": 100,
      "followers": 140,
      "sd": 20,
      "engagements": 23,
      "likes": 19
    }
  },
  {
    "id": "recDE28lBuvcZLz89",
    "createdTime": "2024-08-08T18:39:19.000Z",
    "fields": {
      "Date (GMT)": "2024-08-08 16:46:43",
      "Job Link": "https://dashboard.browse.ai/teams/personal/robots/6b1f28ae-4557-4569-a58b-60e919d89150/history/14b7608f-2c9e-4c88-b657-e1e4a78d64ab",
      "Origin URL": "https://taplio.com/lookup/warikoo",
      "Profile Links Limit": 100,
      "LinkedIn Posts Limit": 100,
      "followers": 2,
      "sd": 20,
      "engagements": 191,
      "likes": 182
    }
  },
  {
    "id": "recDX8jpdoxmqYyMX",
    "createdTime": "2024-08-08T18:39:19.000Z",
    "fields": {
      "Date (GMT)": "2024-08-08 16:44:33",
      "Job Link": "https://dashboard.browse.ai/teams/personal/robots/6b1f28ae-4557-4569-a58b-60e919d89150/history/d970139a-527d-4b2f-b6f6-aaa217fa973e",
      "Origin URL": "https://taplio.com/lookup/jasonmlemkin",
      "Profile Links Limit": 100,
      "LinkedIn Posts Limit": 100,
      "followers": 271,
      "sd": 20,
      "engagements": 6,
      "likes": 5
    }
  },
  {
    "id": "recDai9rbQKTcvYEp",
    "createdTime": "2024-08-08T18:39:19.000Z",
    "fields": {
      "Date (GMT)": "2024-08-08 16:59:46",
      "Job Link": "https://dashboard.browse.ai/teams/personal/robots/6b1f28ae-4557-4569-a58b-60e919d89150/history/8fdac8c3-0014-4053-9c2d-d03bdc417845",
      "Origin URL": "https://taplio.com/lookup/careergurudotco",
      "Profile Links Limit": 100,
      "LinkedIn Posts Limit": 100,
      "followers": 80,
      "sd": 20,
      "engagements": 2,
      "likes": 1
    }
  },
  {
    "id": "recDjlbIQKXix9oxB",
    "createdTime": "2024-08-08T18:39:19.000Z",
    "fields": {
      "Date (GMT)": "2024-08-08 16:44:27",
      "Job Link": "https://dashboard.browse.ai/teams/personal/robots/6b1f28ae-4557-4569-a58b-60e919d89150/history/cbe298f2-4b83-482e-96a3-e637479bd2f2",
      "Origin URL": "https://taplio.com/lookup/vidalmarc",
      "Profile Links Limit": 100,
      "LinkedIn Posts Limit": 100,
      "followers": 624,
      "sd": 20,
      "engagements": 44,
      "likes": 39
    }
  },
  {
    "id": "recEDlUrYCzSym1Or",
    "createdTime": "2024-08-08T18:39:19.000Z",
    "fields": {
      "Date (GMT)": "2024-08-08 16:43:42",
      "Job Link": "https://dashboard.browse.ai/teams/personal/robots/6b1f28ae-4557-4569-a58b-60e919d89150/history/6f3afbf4-5fd6-4f2e-9673-38e9aab547eb",
      "Origin URL": "https://taplio.com/lookup/agazdecki",
      "Profile Links Limit": 100,
      "LinkedIn Posts Limit": 100,
      "followers": 99,
      "sd": 20,
      "engagements": 3,
      "likes": 3
    }
  },
  {
    "id": "recEhSUOREoX9H1ji",
    "createdTime": "2024-08-08T18:39:19.000Z",
    "fields": {
      "Date (GMT)": "2024-08-08 16:53:01",
      "Job Link": "https://dashboard.browse.ai/teams/personal/robots/6b1f28ae-4557-4569-a58b-60e919d89150/history/2f2c22aa-a90b-4015-a44a-30641f351fe1",
      "Origin URL": "https://taplio.com/lookup/stevenbartlett-123",
      "Profile Links Limit": 100,
      "LinkedIn Posts Limit": 100,
      "followers": 2,
      "sd": 20,
      "engagements": 458,
      "likes": 413
    }
  },
  {
    "id": "recFiaQsHbyyKVGqZ",
    "createdTime": "2024-08-08T18:39:19.000Z",
    "fields": {
      "Date (GMT)": "2024-08-08 16:42:14",
      "Job Link": "https://dashboard.browse.ai/teams/personal/robots/6b1f28ae-4557-4569-a58b-60e919d89150/history/51a99709-2cfc-4a3f-9f6d-55acb901297b",
      "Origin URL": "https://taplio.com/lookup/pratik-thakker",
      "Profile Links Limit": 100,
      "LinkedIn Posts Limit": 100,
      "followers": 244,
      "sd": 20,
      "engagements": 5,
      "likes": 5
    }
  },
  {
    "id": "recGIJHtz3OuDeULT",
    "createdTime": "2024-08-08T18:39:19.000Z",
    "fields": {
      "Date (GMT)": "2024-08-08 17:00:56",
      "Job Link": "https://dashboard.browse.ai/teams/personal/robots/6b1f28ae-4557-4569-a58b-60e919d89150/history/b6344ffd-fe95-465c-ba4b-bde2cb513a74",
      "Origin URL": "https://taplio.com/lookup/timaelhajj",
      "Profile Links Limit": 100,
      "LinkedIn Posts Limit": 100,
      "followers": 125,
      "sd": 1,
      "engagements": 444,
      "likes": 358
    }
  },
  {
    "id": "recHCGbiLl6MDfKLx",
    "createdTime": "2024-08-08T18:39:19.000Z",
    "fields": {
      "Date (GMT)": "2024-08-08 16:54:37",
      "Job Link": "https://dashboard.browse.ai/teams/personal/robots/6b1f28ae-4557-4569-a58b-60e919d89150/history/89ebd19f-97ab-4a6b-81bf-9c5224f2527b",
      "Origin URL": "https://taplio.com/lookup/jason-fried",
      "Profile Links Limit": 100,
      "LinkedIn Posts Limit": 100,
      "followers": 137,
      "sd": 10,
      "engagements": 9,
      "likes": 8
    }
  },
  {
    "id": "recHfdlFYsfCi91rl",
    "createdTime": "2024-08-08T18:39:19.000Z",
    "fields": {
      "Date (GMT)": "2024-08-08 16:44:46",
      "Job Link": "https://dashboard.browse.ai/teams/personal/robots/6b1f28ae-4557-4569-a58b-60e919d89150/history/58ab1eb1-4276-45b5-9fdc-138dc9158cc8",
      "Origin URL": "https://taplio.com/lookup/theheathermonahan",
      "Profile Links Limit": 100,
      "LinkedIn Posts Limit": 100,
      "followers": 306,
      "sd": 20,
      "engagements": 21,
      "likes": 17
    }
  },
  {
    "id": "recHls4AlnZTDekSn",
    "createdTime": "2024-08-08T18:39:19.000Z",
    "fields": {
      "Date (GMT)": "2024-08-08 16:42:14",
      "Job Link": "https://dashboard.browse.ai/teams/personal/robots/6b1f28ae-4557-4569-a58b-60e919d89150/history/3b93855b-92ce-4d98-b4bb-c224357a79c1",
      "Origin URL": "https://taplio.com/lookup/michaeljacksonvc",
      "Profile Links Limit": 100,
      "LinkedIn Posts Limit": 100,
      "followers": 200,
      "sd": 20,
      "engagements": 39,
      "likes": 36
    }
  },
  {
    "id": "recHmSYrz9fCPyUDN",
    "createdTime": "2024-08-08T18:39:19.000Z",
    "fields": {
      "Date (GMT)": "2024-08-08 16:48:10",
      "Job Link": "https://dashboard.browse.ai/teams/personal/robots/6b1f28ae-4557-4569-a58b-60e919d89150/history/4dec0c8d-ed90-4740-af58-84382d8f8370",
      "Origin URL": "https://taplio.com/lookup/markalansamuel",
      "Profile Links Limit": 100,
      "LinkedIn Posts Limit": 100,
      "followers": 62,
      "sd": 2,
      "engagements": 487,
      "likes": 387
    }
  },
  {
    "id": "recHznAl9uLPyzQBW",
    "createdTime": "2024-08-08T18:39:19.000Z",
    "fields": {
      "Date (GMT)": "2024-08-08 16:50:51",
      "Job Link": "https://dashboard.browse.ai/teams/personal/robots/6b1f28ae-4557-4569-a58b-60e919d89150/history/1c418ad8-a2e7-46b3-9cf9-d217862e079e",
      "Origin URL": "https://taplio.com/lookup/nancy-pezarkar",
      "Profile Links Limit": 100,
      "LinkedIn Posts Limit": 100,
      "followers": 85,
      "sd": 20,
      "engagements": 5,
      "likes": 5
    }
  },
  {
    "id": "recJ6d4O3VEavNGur",
    "createdTime": "2024-08-08T18:39:19.000Z",
    "fields": {
      "Date (GMT)": "2024-08-08 16:55:21",
      "Job Link": "https://dashboard.browse.ai/teams/personal/robots/6b1f28ae-4557-4569-a58b-60e919d89150/history/1afdfac8-64f1-4c60-9158-fc7f14bc17c7",
      "Origin URL": "https://taplio.com/lookup/daniel-murray-marketing",
      "Profile Links Limit": 100,
      "LinkedIn Posts Limit": 100,
      "followers": 138,
      "sd": 7,
      "engagements": 5,
      "likes": 4
    }
  },
  {
    "id": "recJX8lsuTHjJHhOK",
    "createdTime": "2024-08-08T18:39:19.000Z",
    "fields": {
      "Date (GMT)": "2024-08-08 17:13:44",
      "Job Link": "https://dashboard.browse.ai/teams/personal/robots/6b1f28ae-4557-4569-a58b-60e919d89150/history/e08da774-b735-4cca-a842-7590f5e7a091",
      "Origin URL": "https://taplio.com/lookup/shivshivakumar",
      "Profile Links Limit": 100,
      "LinkedIn Posts Limit": 100,
      "followers": 123,
      "sd": 1,
      "engagements": 167,
      "likes": 155
    }
  },
  {
    "id": "recJcoWqRSEJafxiT",
    "createdTime": "2024-08-08T18:39:19.000Z",
    "fields": {
      "Date (GMT)": "2024-08-08 16:38:45",
      "Job Link": "https://dashboard.browse.ai/teams/personal/robots/6b1f28ae-4557-4569-a58b-60e919d89150/history/389d7050-faf8-45d6-a7f9-7be2c05efacf",
      "Origin URL": "https://taplio.com/lookup/marcelvanoost",
      "Profile Links Limit": 100,
      "LinkedIn Posts Limit": 100,
      "followers": 158,
      "sd": 20,
      "engagements": 45,
      "likes": 41
    }
  },
  {
    "id": "recKiG6G7ISon4bOW",
    "createdTime": "2024-08-08T18:39:19.000Z",
    "fields": {
      "Date (GMT)": "2024-08-08 17:00:07",
      "Job Link": "https://dashboard.browse.ai/teams/personal/robots/6b1f28ae-4557-4569-a58b-60e919d89150/history/e5a62635-1bd0-4258-8260-96f3f81c9c86",
      "Origin URL": "https://taplio.com/lookup/davidalto",
      "Profile Links Limit": 100,
      "LinkedIn Posts Limit": 100,
      "followers": 135,
      "sd": 18,
      "engagements": 2,
      "likes": 2
    }
  },
  {
    "id": "recKmePeQyARN1IOH",
    "createdTime": "2024-08-08T18:39:19.000Z",
    "fields": {
      "Date (GMT)": "2024-08-08 17:04:06",
      "Job Link": "https://dashboard.browse.ai/teams/personal/robots/6b1f28ae-4557-4569-a58b-60e919d89150/history/d29cba69-95a0-4b33-ae64-a63bbb3f9eeb",
      "Origin URL": "https://taplio.com/lookup/rharris415",
      "Profile Links Limit": 100,
      "LinkedIn Posts Limit": 100,
      "followers": 57,
      "sd": 20,
      "engagements": 588,
      "likes": 397
    }
  },
  {
    "id": "recKv944BdfbI9O9S",
    "createdTime": "2024-08-08T18:39:19.000Z",
    "fields": {
      "Date (GMT)": "2024-08-08 16:46:59",
      "Job Link": "https://dashboard.browse.ai/teams/personal/robots/6b1f28ae-4557-4569-a58b-60e919d89150/history/befec5bc-3d0b-4825-a1b4-fabf8e9749c1",
      "Origin URL": "https://taplio.com/lookup/houstongolden",
      "Profile Links Limit": 100,
      "LinkedIn Posts Limit": 100,
      "followers": 135,
      "sd": 20,
      "engagements": 4,
      "likes": 3
    }
  },
  {
    "id": "recMhQ5wYTjUF7nFT",
    "createdTime": "2024-08-08T18:39:19.000Z",
    "fields": {
      "Date (GMT)": "2024-08-08 16:43:46",
      "Job Link": "https://dashboard.browse.ai/teams/personal/robots/6b1f28ae-4557-4569-a58b-60e919d89150/history/ea79eed6-d77f-4198-a56c-9fb52514d85d",
      "Origin URL": "https://taplio.com/lookup/aprillatoyalittle",
      "Profile Links Limit": 100,
      "LinkedIn Posts Limit": 100,
      "followers": 235,
      "sd": 20,
      "engagements": 38,
      "likes": 33
    }
  },
  {
    "id": "recMpesy1HPtJV7si",
    "createdTime": "2024-08-08T18:39:19.000Z",
    "fields": {
      "Date (GMT)": "2024-08-08 16:45:42",
      "Job Link": "https://dashboard.browse.ai/teams/personal/robots/6b1f28ae-4557-4569-a58b-60e919d89150/history/744860c7-6406-4f58-bd47-74134e5c5857",
      "Origin URL": "https://taplio.com/lookup/ahmadshassan",
      "Profile Links Limit": 100,
      "LinkedIn Posts Limit": 100,
      "followers": 180,
      "sd": 20,
      "engagements": 97,
      "likes": 89
    }
  },
  {
    "id": "recNEKQ91TMOhAgjP",
    "createdTime": "2024-08-08T18:39:19.000Z",
    "fields": {
      "Date (GMT)": "2024-08-08 16:50:40",
      "Job Link": "https://dashboard.browse.ai/teams/personal/robots/6b1f28ae-4557-4569-a58b-60e919d89150/history/bbc0e278-5b38-4017-bb43-c4e3e86b7dcb",
      "Origin URL": "https://taplio.com/lookup/lukematthws",
      "Profile Links Limit": 100,
      "LinkedIn Posts Limit": 100,
      "followers": 165,
      "sd": 20,
      "engagements": 45,
      "likes": 21
    }
  },
  {
    "id": "recOE9B2Fn2w6TjA9",
    "createdTime": "2024-08-08T18:39:19.000Z",
    "fields": {
      "Date (GMT)": "2024-08-08 16:49:26",
      "Job Link": "https://dashboard.browse.ai/teams/personal/robots/6b1f28ae-4557-4569-a58b-60e919d89150/history/49d2855c-2310-41cc-9c23-dde171a03334",
      "Origin URL": "https://taplio.com/lookup/amewborn",
      "Profile Links Limit": 100,
      "LinkedIn Posts Limit": 100,
      "followers": 186,
      "sd": 11,
      "engagements": 2,
      "likes": 1
    }
  },
  {
    "id": "recOK2JConqA8fB9w",
    "createdTime": "2024-08-08T18:39:19.000Z",
    "fields": {
      "Date (GMT)": "2024-08-08 16:54:23",
      "Job Link": "https://dashboard.browse.ai/teams/personal/robots/6b1f28ae-4557-4569-a58b-60e919d89150/history/5c02a4cb-e546-416a-a61c-4569925751f4",
      "Origin URL": "https://taplio.com/lookup/pierre-herubel-540b3949",
      "Profile Links Limit": 100,
      "LinkedIn Posts Limit": 100,
      "followers": 107,
      "sd": 20,
      "engagements": 21,
      "likes": 16
    }
  },
  {
    "id": "recOytocsLw1TUzXM",
    "createdTime": "2024-08-08T18:39:19.000Z",
    "fields": {
      "Date (GMT)": "2024-08-08 17:01:38",
      "Job Link": "https://dashboard.browse.ai/teams/personal/robots/6b1f28ae-4557-4569-a58b-60e919d89150/history/b5965876-17e0-49bd-a6c8-af356f24ed82",
      "Origin URL": "https://taplio.com/lookup/deepanshuk",
      "Profile Links Limit": 100,
      "LinkedIn Posts Limit": 100,
      "followers": 75,
      "sd": 2,
      "engagements": 665,
      "likes": 606
    }
  },
  {
    "id": "recPg1fAm5TZp8fwa",
    "createdTime": "2024-08-08T18:39:19.000Z",
    "fields": {
      "Date (GMT)": "2024-08-08 16:46:54",
      "Job Link": "https://dashboard.browse.ai/teams/personal/robots/6b1f28ae-4557-4569-a58b-60e919d89150/history/95a4297d-da21-4293-af85-37fc070da195",
      "Origin URL": "https://taplio.com/lookup/mattgray1",
      "Profile Links Limit": 100,
      "LinkedIn Posts Limit": 100,
      "followers": 621,
      "sd": 20,
      "engagements": 91,
      "likes": 74
    }
  },
  {
    "id": "recQNCHOPyQGw9m2j",
    "createdTime": "2024-08-08T18:39:19.000Z",
    "fields": {
      "Date (GMT)": "2024-08-08 17:02:57",
      "Job Link": "https://dashboard.browse.ai/teams/personal/robots/6b1f28ae-4557-4569-a58b-60e919d89150/history/cfa887d3-8405-41c5-b90c-9eb802982145",
      "Origin URL": "https://taplio.com/lookup/copierwarrior",
      "Profile Links Limit": 100,
      "LinkedIn Posts Limit": 100,
      "followers": 75,
      "sd": 20,
      "engagements": 6,
      "likes": 4
    }
  },
  {
    "id": "recQsw7JqL2seyUR9",
    "createdTime": "2024-08-08T18:39:19.000Z",
    "fields": {
      "Date (GMT)": "2024-08-08 17:03:58",
      "Job Link": "https://dashboard.browse.ai/teams/personal/robots/6b1f28ae-4557-4569-a58b-60e919d89150/history/278a6001-9909-4b29-91c7-8e04dabd5c8b",
      "Origin URL": "https://taplio.com/lookup/jigar-thakker",
      "Profile Links Limit": 100,
      "LinkedIn Posts Limit": 100,
      "followers": 104,
      "sd": 20,
      "engagements": 5,
      "likes": 4
    }
  },
  {
    "id": "recR76kBGLyr1R2qJ",
    "createdTime": "2024-08-08T18:39:19.000Z",
    "fields": {
      "Date (GMT)": "2024-08-08 16:56:34",
      "Job Link": "https://dashboard.browse.ai/teams/personal/robots/6b1f28ae-4557-4569-a58b-60e919d89150/history/25c5c214-2028-4173-a15f-347d6c593805",
      "Origin URL": "https://taplio.com/lookup/darrenmckeesales",
      "Profile Links Limit": 100,
      "LinkedIn Posts Limit": 100,
      "followers": 116,
      "sd": 20,
      "engagements": 10,
      "likes": 6
    }
  },
  {
    "id": "recSi2nj1RtQFd4vD",
    "createdTime": "2024-08-08T18:39:19.000Z",
    "fields": {
      "Date (GMT)": "2024-08-08 16:59:04",
      "Job Link": "https://dashboard.browse.ai/teams/personal/robots/6b1f28ae-4557-4569-a58b-60e919d89150/history/6829bd4c-2988-4c17-8de5-8e2f0e70be64",
      "Origin URL": "https://taplio.com/lookup/lanphan",
      "Profile Links Limit": 100,
      "LinkedIn Posts Limit": 100,
      "followers": 118,
      "sd": 2,
      "engagements": 2,
      "likes": 2
    }
  },
  {
    "id": "recTsIjYKU3dvPiCj",
    "createdTime": "2024-08-08T18:39:19.000Z",
    "fields": {
      "Date (GMT)": "2024-08-08 16:43:49",
      "Job Link": "https://dashboard.browse.ai/teams/personal/robots/6b1f28ae-4557-4569-a58b-60e919d89150/history/16d20887-5909-4ed7-9feb-145cce6a9eea",
      "Origin URL": "https://taplio.com/lookup/colby-kultgen",
      "Profile Links Limit": 100,
      "LinkedIn Posts Limit": 100,
      "followers": 316,
      "sd": 20,
      "engagements": 91,
      "likes": 76
    }
  },
  {
    "id": "recVrU1c4I6HATXzb",
    "createdTime": "2024-08-08T18:39:19.000Z",
    "fields": {
      "Date (GMT)": "2024-08-08 17:03:48",
      "Job Link": "https://dashboard.browse.ai/teams/personal/robots/6b1f28ae-4557-4569-a58b-60e919d89150/history/09c91600-403e-4fac-beaa-4f65b9c90920",
      "Origin URL": "https://taplio.com/lookup/salmanmohiuddin",
      "Profile Links Limit": 100,
      "LinkedIn Posts Limit": 100,
      "followers": 84,
      "sd": 18,
      "engagements": 4,
      "likes": 3
    }
  },
  {
    "id": "recW633q7Wg0Sbuho",
    "createdTime": "2024-08-08T18:39:19.000Z",
    "fields": {
      "Date (GMT)": "2024-08-08 16:38:48",
      "Job Link": "https://dashboard.browse.ai/teams/personal/robots/6b1f28ae-4557-4569-a58b-60e919d89150/history/916350c0-ab10-4f44-bec2-e7143f167413",
      "Origin URL": "https://taplio.com/lookup/alexhormozi",
      "Profile Links Limit": 100,
      "LinkedIn Posts Limit": 100,
      "followers": 420,
      "sd": 20,
      "engagements": 114,
      "likes": 98
    }
  },
  {
    "id": "recWfbvC8Hf4BLEEA",
    "createdTime": "2024-08-08T18:39:19.000Z",
    "fields": {
      "Date (GMT)": "2024-08-08 16:41:26",
      "Job Link": "https://dashboard.browse.ai/teams/personal/robots/6b1f28ae-4557-4569-a58b-60e919d89150/history/b2102a13-ba96-41bd-a242-f3ee30011edb",
      "Origin URL": "https://taplio.com/lookup/josh-braun",
      "Profile Links Limit": 100,
      "LinkedIn Posts Limit": 100,
      "followers": 227,
      "sd": 20,
      "engagements": 9,
      "likes": 8
    }
  },
  {
    "id": "recWteys50MUEZsVs",
    "createdTime": "2024-08-08T18:39:19.000Z",
    "fields": {
      "Date (GMT)": "2024-08-08 16:57:46",
      "Job Link": "https://dashboard.browse.ai/teams/personal/robots/6b1f28ae-4557-4569-a58b-60e919d89150/history/e0e5cd15-12dd-4fdf-863b-72799d2242d4",
      "Origin URL": "https://taplio.com/lookup/lexfridman",
      "Profile Links Limit": 100,
      "LinkedIn Posts Limit": 100,
      "followers": 1,
      "sd": 20,
      "engagements": 296,
      "likes": 278
    }
  },
  {
    "id": "recX3OskLvKth0fgg",
    "createdTime": "2024-08-08T18:39:19.000Z",
    "fields": {
      "Date (GMT)": "2024-08-08 17:03:02",
      "Job Link": "https://dashboard.browse.ai/teams/personal/robots/6b1f28ae-4557-4569-a58b-60e919d89150/history/2b031fe3-91c2-4c07-b98e-b86a2168cfdd",
      "Origin URL": "https://taplio.com/lookup/ericarankin777",
      "Profile Links Limit": 100,
      "LinkedIn Posts Limit": 100,
      "followers": 71,
      "sd": 12,
      "engagements": 8,
      "likes": 6
    }
  },
  {
    "id": "recXDySGfwT5GnBID",
    "createdTime": "2024-08-08T18:39:19.000Z",
    "fields": {
      "Date (GMT)": "2024-08-08 16:44:50",
      "Job Link": "https://dashboard.browse.ai/teams/personal/robots/6b1f28ae-4557-4569-a58b-60e919d89150/history/b07e56f1-5754-4fb2-b9e9-f507302d16f1",
      "Origin URL": "https://taplio.com/lookup/juanjosedelgado",
      "Profile Links Limit": 100,
      "LinkedIn Posts Limit": 100,
      "followers": 215,
      "sd": 20,
      "engagements": 77,
      "likes": 65
    }
  },
  {
    "id": "recXYLufDlqf2C3Tk",
    "createdTime": "2024-08-08T18:39:19.000Z",
    "fields": {
      "Date (GMT)": "2024-08-08 16:51:53",
      "Job Link": "https://dashboard.browse.ai/teams/personal/robots/6b1f28ae-4557-4569-a58b-60e919d89150/history/eaacd7d9-5e43-4035-aec1-711802ab7d77",
      "Origin URL": "https://taplio.com/lookup/jehakjerrylee",
      "Profile Links Limit": 100,
      "LinkedIn Posts Limit": 100,
      "followers": 388,
      "sd": 20,
      "engagements": 32,
      "likes": 29
    }
  },
  {
    "id": "recY9N3uJN2du5SjE",
    "createdTime": "2024-08-08T18:39:19.000Z",
    "fields": {
      "Date (GMT)": "2024-08-08 16:53:43",
      "Job Link": "https://dashboard.browse.ai/teams/personal/robots/6b1f28ae-4557-4569-a58b-60e919d89150/history/13a45760-ec56-4368-92d2-37ecfd712b83",
      "Origin URL": "https://taplio.com/lookup/pascalbornet",
      "Profile Links Limit": 100,
      "LinkedIn Posts Limit": 100,
      "followers": 1,
      "sd": 20,
      "engagements": 171,
      "likes": 152
    }
  },
  {
    "id": "recdUPAeD6Hn5SKnr",
    "createdTime": "2024-08-08T18:39:19.000Z",
    "fields": {
      "Date (GMT)": "2024-08-08 17:06:42",
      "Job Link": "https://dashboard.browse.ai/teams/personal/robots/6b1f28ae-4557-4569-a58b-60e919d89150/history/a69b99b9-71ef-4ed7-af1f-5ee89627ba59",
      "Origin URL": "https://taplio.com/lookup/itschrisoconnell",
      "Profile Links Limit": 100,
      "LinkedIn Posts Limit": 100,
      "followers": 72,
      "sd": 20,
      "engagements": 3,
      "likes": 1
    }
  },
  {
    "id": "recdfnsMTTSbmUoPp",
    "createdTime": "2024-08-08T18:39:19.000Z",
    "fields": {
      "Date (GMT)": "2024-08-08 16:55:30",
      "Job Link": "https://dashboard.browse.ai/teams/personal/robots/6b1f28ae-4557-4569-a58b-60e919d89150/history/d60980df-d39f-4662-9242-c10e72f28fdc",
      "Origin URL": "https://taplio.com/lookup/ralph-aboujaoude-diaz-40838313",
      "Profile Links Limit": 100,
      "LinkedIn Posts Limit": 100,
      "followers": 95,
      "sd": 20,
      "engagements": 20,
      "likes": 18
    }
  },
  {
    "id": "recdlSCrFcJ973IR4",
    "createdTime": "2024-08-08T18:39:19.000Z",
    "fields": {
      "Date (GMT)": "2024-08-08 16:51:55",
      "Job Link": "https://dashboard.browse.ai/teams/personal/robots/6b1f28ae-4557-4569-a58b-60e919d89150/history/95653436-3ab7-4e49-82f2-630ede9f919b",
      "Origin URL": "https://taplio.com/lookup/morganjingram",
      "Profile Links Limit": 100,
      "LinkedIn Posts Limit": 100,
      "followers": 164,
      "sd": 20,
      "engagements": 8,
      "likes": 5
    }
  },
  {
    "id": "recfYmqgf9dQrxuvG",
    "createdTime": "2024-08-08T18:39:19.000Z",
    "fields": {
      "Date (GMT)": "2024-08-08 16:38:08",
      "Job Link": "https://dashboard.browse.ai/teams/personal/robots/6b1f28ae-4557-4569-a58b-60e919d89150/history/2188f00d-2c11-4c5a-9c2b-d46357ea0c7c",
      "Origin URL": "https://taplio.com/lookup/linasbeliunas",
      "Profile Links Limit": 100,
      "LinkedIn Posts Limit": 100,
      "followers": 509,
      "sd": 20,
      "engagements": 114,
      "likes": 96
    }
  },
  {
    "id": "recfoz2guvRZR4YMZ",
    "createdTime": "2024-08-08T18:39:19.000Z",
    "fields": {
      "Date (GMT)": "2024-08-08 16:45:44",
      "Job Link": "https://dashboard.browse.ai/teams/personal/robots/6b1f28ae-4557-4569-a58b-60e919d89150/history/2d6b7920-1f9a-4011-8db1-6ef9a661eded",
      "Origin URL": "https://taplio.com/lookup/chrisorlob",
      "Profile Links Limit": 100,
      "LinkedIn Posts Limit": 100,
      "followers": 142,
      "sd": 20,
      "engagements": 9,
      "likes": 8
    }
  },
  {
    "id": "recgMTGkXRRq1sXsI",
    "createdTime": "2024-08-08T18:39:19.000Z",
    "fields": {
      "Date (GMT)": "2024-08-08 17:02:44",
      "Job Link": "https://dashboard.browse.ai/teams/personal/robots/6b1f28ae-4557-4569-a58b-60e919d89150/history/d448c89b-a63a-432d-9e6a-3530171452ca",
      "Origin URL": "https://taplio.com/lookup/maryhendersoncoaching",
      "Profile Links Limit": 100,
      "LinkedIn Posts Limit": 100,
      "followers": 79,
      "sd": 20,
      "engagements": 713,
      "likes": 461
    }
  },
  {
    "id": "rechkp7u16Cy5qEXU",
    "createdTime": "2024-08-08T18:39:19.000Z",
    "fields": {
      "Date (GMT)": "2024-08-08 16:46:55",
      "Job Link": "https://dashboard.browse.ai/teams/personal/robots/6b1f28ae-4557-4569-a58b-60e919d89150/history/c4c114cd-9e81-4a07-b166-376450775554",
      "Origin URL": "https://taplio.com/lookup/joergstorm",
      "Profile Links Limit": 100,
      "LinkedIn Posts Limit": 100,
      "followers": 625,
      "sd": 20,
      "engagements": 67,
      "likes": 57
    }
  },
  {
    "id": "rechrYo9PQqK3f7nD",
    "createdTime": "2024-08-08T18:39:19.000Z",
    "fields": {
      "Date (GMT)": "2024-08-08 16:57:07",
      "Job Link": "https://dashboard.browse.ai/teams/personal/robots/6b1f28ae-4557-4569-a58b-60e919d89150/history/daa49597-3c1e-4a1f-a677-e56a86fd2a84",
      "Origin URL": "https://taplio.com/lookup/chenae-erkerd-j-d-racr-798b2389",
      "Profile Links Limit": 100,
      "LinkedIn Posts Limit": 100,
      "followers": 126,
      "sd": 11,
      "engagements": 5,
      "likes": 4
    }
  },
  {
    "id": "recj0INQ2zuHNNop0",
    "createdTime": "2024-08-08T18:39:19.000Z",
    "fields": {
      "Date (GMT)": "2024-08-08 16:44:39",
      "Job Link": "https://dashboard.browse.ai/teams/personal/robots/6b1f28ae-4557-4569-a58b-60e919d89150/history/6359e553-8790-4eb4-a0fb-5052b47c0afa",
      "Origin URL": "https://taplio.com/lookup/michaelaguilarconferencier",
      "Profile Links Limit": 100,
      "LinkedIn Posts Limit": 100,
      "followers": 370,
      "sd": 20,
      "engagements": 59,
      "likes": 50
    }
  },
  {
    "id": "recjaZPZ5TyOcW72w",
    "createdTime": "2024-08-08T18:39:19.000Z",
    "fields": {
      "Date (GMT)": "2024-08-08 16:49:21",
      "Job Link": "https://dashboard.browse.ai/teams/personal/robots/6b1f28ae-4557-4569-a58b-60e919d89150/history/efb9d957-2286-4a00-a151-f298a4953927",
      "Origin URL": "https://taplio.com/lookup/htaha",
      "Profile Links Limit": 100,
      "LinkedIn Posts Limit": 100,
      "followers": 245,
      "sd": 20,
      "engagements": 59,
      "likes": 53
    }
  },
  {
    "id": "reckgITd0aSpDgkfW",
    "createdTime": "2024-08-08T18:39:19.000Z",
    "fields": {
      "Date (GMT)": "2024-08-08 16:53:40",
      "Job Link": "https://dashboard.browse.ai/teams/personal/robots/6b1f28ae-4557-4569-a58b-60e919d89150/history/83a7d6e8-df11-4f2e-b882-353bae66213d",
      "Origin URL": "https://taplio.com/lookup/thibaultll",
      "Profile Links Limit": 100,
      "LinkedIn Posts Limit": 100,
      "followers": 23,
      "sd": 20,
      "engagements": 1,
      "likes": 1
    }
  },
  {
    "id": "reckjex1crT9SNX4p",
    "createdTime": "2024-08-08T18:39:19.000Z",
    "fields": {
      "Date (GMT)": "2024-08-08 17:03:54",
      "Job Link": "https://dashboard.browse.ai/teams/personal/robots/6b1f28ae-4557-4569-a58b-60e919d89150/history/0053a0a7-ffaf-4728-b918-5ef81e28ca79",
      "Origin URL": "https://taplio.com/lookup/yadavajay",
      "Profile Links Limit": 100,
      "LinkedIn Posts Limit": 100,
      "followers": 112,
      "sd": 14,
      "engagements": 1,
      "likes": 1
    }
  },
  {
    "id": "reckzDSX7E9WN16yu",
    "createdTime": "2024-08-08T18:39:19.000Z",
    "fields": {
      "Date (GMT)": "2024-08-08 17:09:36",
      "Job Link": "https://dashboard.browse.ai/teams/personal/robots/6b1f28ae-4557-4569-a58b-60e919d89150/history/8ce9a941-2089-42a6-ae01-eb29600f39db",
      "Origin URL": "https://taplio.com/lookup/sellwithdean",
      "Profile Links Limit": 100,
      "LinkedIn Posts Limit": 100,
      "followers": 68,
      "sd": 20,
      "engagements": 5,
      "likes": 4
    }
  },
  {
    "id": "recljzRwAEOzcRxgt",
    "createdTime": "2024-08-08T18:39:19.000Z",
    "fields": {
      "Date (GMT)": "2024-08-08 16:37:39",
      "Job Link": "https://dashboard.browse.ai/teams/personal/robots/6b1f28ae-4557-4569-a58b-60e919d89150/history/e5ba96a3-fa91-4406-bfd2-4f6c46ad8b82",
      "Origin URL": "https://taplio.com/lookup/donnellychris",
      "Profile Links Limit": 100,
      "LinkedIn Posts Limit": 100,
      "followers": 740,
      "sd": 20,
      "engagements": 846,
      "likes": 752
    }
  },
  {
    "id": "reclrX1kzmUp6r0D2",
    "createdTime": "2024-08-08T18:39:19.000Z",
    "fields": {
      "Date (GMT)": "2024-08-08 16:42:40",
      "Job Link": "https://dashboard.browse.ai/teams/personal/robots/6b1f28ae-4557-4569-a58b-60e919d89150/history/c334fd79-1611-4d28-9bff-525a9369ce0e",
      "Origin URL": "https://taplio.com/lookup/jacobaaronbrown",
      "Profile Links Limit": 100,
      "LinkedIn Posts Limit": 100,
      "followers": 53,
      "sd": 20,
      "engagements": 5,
      "likes": 4
    }
  },
  {
    "id": "recmBBBQFi7ng6sGB",
    "createdTime": "2024-08-08T18:39:19.000Z",
    "fields": {
      "Date (GMT)": "2024-08-08 17:09:54",
      "Job Link": "https://dashboard.browse.ai/teams/personal/robots/6b1f28ae-4557-4569-a58b-60e919d89150/history/f70697b2-e195-4eb4-8383-b30560f8ed10",
      "Origin URL": "https://taplio.com/lookup/jasonvana",
      "Profile Links Limit": 100,
      "LinkedIn Posts Limit": 100,
      "followers": 75,
      "sd": 20,
      "engagements": 8,
      "likes": 4
    }
  },
  {
    "id": "recmnXyaAELPb7Vin",
    "createdTime": "2024-08-08T18:39:19.000Z",
    "fields": {
      "Date (GMT)": "2024-08-08 16:39:57",
      "Job Link": "https://dashboard.browse.ai/teams/personal/robots/6b1f28ae-4557-4569-a58b-60e919d89150/history/65f22276-b860-4925-a9fd-90c98ef1bcde",
      "Origin URL": "https://taplio.com/lookup/chasedimond",
      "Profile Links Limit": 100,
      "LinkedIn Posts Limit": 100,
      "followers": 325,
      "sd": 20,
      "engagements": 85,
      "likes": 73
    }
  },
  {
    "id": "recmovfN0j6FIcCgf",
    "createdTime": "2024-08-08T18:39:19.000Z",
    "fields": {
      "Date (GMT)": "2024-08-08 16:43:41",
      "Job Link": "https://dashboard.browse.ai/teams/personal/robots/6b1f28ae-4557-4569-a58b-60e919d89150/history/961afb20-6a91-412a-a1d4-7abc6c85dbca",
      "Origin URL": "https://taplio.com/lookup/benoitdubos",
      "Profile Links Limit": 100,
      "LinkedIn Posts Limit": 100,
      "followers": 126,
      "sd": 20,
      "engagements": 6,
      "likes": 4
    }
  },
  {
    "id": "recnWUOZjhsyHW1Tn",
    "createdTime": "2024-08-08T18:39:19.000Z",
    "fields": {
      "Date (GMT)": "2024-08-08 16:41:30",
      "Job Link": "https://dashboard.browse.ai/teams/personal/robots/6b1f28ae-4557-4569-a58b-60e919d89150/history/e707743f-b417-49a0-ab3a-03b1f9b5c5c5",
      "Origin URL": "https://taplio.com/lookup/sahilbloom",
      "Profile Links Limit": 100,
      "LinkedIn Posts Limit": 100,
      "followers": 576,
      "sd": 20,
      "engagements": 41,
      "likes": 33
    }
  },
  {
    "id": "recnwuMAWPof3PGNF",
    "createdTime": "2024-08-08T18:39:19.000Z",
    "fields": {
      "Date (GMT)": "2024-08-08 16:58:26",
      "Job Link": "https://dashboard.browse.ai/teams/personal/robots/6b1f28ae-4557-4569-a58b-60e919d89150/history/99e790da-59a8-406e-bcad-b8f969fd1918",
      "Origin URL": "https://taplio.com/lookup/devinreed",
      "Profile Links Limit": 100,
      "LinkedIn Posts Limit": 100,
      "followers": 84,
      "sd": 20,
      "engagements": 5,
      "likes": 4
    }
  },
  {
    "id": "recoDiTa9Vaft6Bet",
    "createdTime": "2024-08-08T18:39:19.000Z",
    "fields": {
      "Date (GMT)": "2024-08-08 17:02:55",
      "Job Link": "https://dashboard.browse.ai/teams/personal/robots/6b1f28ae-4557-4569-a58b-60e919d89150/history/05d6b0c2-5a52-4e5c-ac99-e0d6b2531f65",
      "Origin URL": "https://taplio.com/lookup/ryancwalsh",
      "Profile Links Limit": 100,
      "LinkedIn Posts Limit": 100,
      "followers": 107,
      "sd": 2,
      "engagements": 4,
      "likes": 4
    }
  },
  {
    "id": "recoHeNw6ooTFzRRK",
    "createdTime": "2024-08-08T18:39:19.000Z",
    "fields": {
      "Date (GMT)": "2024-08-08 16:54:44",
      "Job Link": "https://dashboard.browse.ai/teams/personal/robots/6b1f28ae-4557-4569-a58b-60e919d89150/history/48c6fd65-afad-424b-bd82-ca07617932c4",
      "Origin URL": "https://taplio.com/lookup/jordan-nelson-salesforce",
      "Profile Links Limit": 100,
      "LinkedIn Posts Limit": 100,
      "followers": 95,
      "sd": 20,
      "engagements": 6,
      "likes": 5
    }
  },
  {
    "id": "recoNOqapw1cTampn",
    "createdTime": "2024-08-08T18:39:19.000Z",
    "fields": {
      "Date (GMT)": "2024-08-08 16:41:29",
      "Job Link": "https://dashboard.browse.ai/teams/personal/robots/6b1f28ae-4557-4569-a58b-60e919d89150/history/fb1c44b0-f217-494c-8fbc-396a9aeed7eb",
      "Origin URL": "https://taplio.com/lookup/robynnstorey",
      "Profile Links Limit": 100,
      "LinkedIn Posts Limit": 100,
      "followers": 998,
      "sd": 20,
      "engagements": 120,
      "likes": 111
    }
  },
  {
    "id": "recpKH9oL2xsqK4MN",
    "createdTime": "2024-08-08T18:39:19.000Z",
    "fields": {
      "Date (GMT)": "2024-08-08 16:56:25",
      "Job Link": "https://dashboard.browse.ai/teams/personal/robots/6b1f28ae-4557-4569-a58b-60e919d89150/history/4b6c3510-50a9-45ef-afa2-2f8e179ce2b2",
      "Origin URL": "https://taplio.com/lookup/andreaiorio",
      "Profile Links Limit": 100,
      "LinkedIn Posts Limit": 100,
      "followers": 71,
      "sd": 5,
      "engagements": 379,
      "likes": 306
    }
  },
  {
    "id": "recpkFhFViE5pR0Wl",
    "createdTime": "2024-08-08T18:39:19.000Z",
    "fields": {
      "Date (GMT)": "2024-08-08 16:50:55",
      "Job Link": "https://dashboard.browse.ai/teams/personal/robots/6b1f28ae-4557-4569-a58b-60e919d89150/history/7267fe08-f1b7-40db-b6c5-3c447474ad07",
      "Origin URL": "https://taplio.com/lookup/mattjbarker1",
      "Profile Links Limit": 100,
      "LinkedIn Posts Limit": 100,
      "followers": 145,
      "sd": 20,
      "engagements": 15,
      "likes": 10
    }
  },
  {
    "id": "recqYjMJcrA7siycJ",
    "createdTime": "2024-08-08T18:39:19.000Z",
    "fields": {
      "Date (GMT)": "2024-08-08 16:45:47",
      "Job Link": "https://dashboard.browse.ai/teams/personal/robots/6b1f28ae-4557-4569-a58b-60e919d89150/history/7ca82e55-4ab1-4a06-9026-24ffa782d4a3",
      "Origin URL": "https://taplio.com/lookup/victoria-repa-115a1987",
      "Profile Links Limit": 100,
      "LinkedIn Posts Limit": 100,
      "followers": 274,
      "sd": 20,
      "engagements": 133,
      "likes": 113
    }
  },
  {
    "id": "recqaVFvqYNK6OqgN",
    "createdTime": "2024-08-08T18:39:19.000Z",
    "fields": {
      "Date (GMT)": "2024-08-08 16:48:25",
      "Job Link": "https://dashboard.browse.ai/teams/personal/robots/6b1f28ae-4557-4569-a58b-60e919d89150/history/2a081d5d-e67b-452b-a518-e8dcad6cbe2a",
      "Origin URL": "https://taplio.com/lookup/renoperry",
      "Profile Links Limit": 100,
      "LinkedIn Posts Limit": 100,
      "followers": 332,
      "sd": 20,
      "engagements": 195,
      "likes": 169
    }
  },
  {
    "id": "recqojPObAkVWSKLg",
    "createdTime": "2024-08-08T18:39:19.000Z",
    "fields": {
      "Date (GMT)": "2024-08-08 16:43:57",
      "Job Link": "https://dashboard.browse.ai/teams/personal/robots/6b1f28ae-4557-4569-a58b-60e919d89150/history/c3a22298-3a65-46cc-8c87-bc038ed92557",
      "Origin URL": "https://taplio.com/lookup/samsalesli",
      "Profile Links Limit": 100,
      "LinkedIn Posts Limit": 100,
      "followers": 95,
      "sd": 20,
      "engagements": 5,
      "likes": 4
    }
  },
  {
    "id": "recqpbZ2NZQsfm8xF",
    "createdTime": "2024-08-08T18:39:19.000Z",
    "fields": {
      "Date (GMT)": "2024-08-08 17:05:30",
      "Job Link": "https://dashboard.browse.ai/teams/personal/robots/6b1f28ae-4557-4569-a58b-60e919d89150/history/0b18f1d0-28d4-4578-8581-b87720c4a921",
      "Origin URL": "https://taplio.com/lookup/kddorsey3",
      "Profile Links Limit": 100,
      "LinkedIn Posts Limit": 100,
      "followers": 124,
      "sd": 20,
      "engagements": 9,
      "likes": 7
    }
  },
  {
    "id": "recr39afandgts3j1",
    "createdTime": "2024-08-08T18:39:19.000Z",
    "fields": {
      "Date (GMT)": "2024-08-08 16:48:28",
      "Job Link": "https://dashboard.browse.ai/teams/personal/robots/6b1f28ae-4557-4569-a58b-60e919d89150/history/bf9ea140-92d4-4c3a-a87b-1c8f604c0079",
      "Origin URL": "https://taplio.com/lookup/garyvaynerchuk",
      "Profile Links Limit": 100,
      "LinkedIn Posts Limit": 100,
      "followers": 5,
      "sd": 20,
      "engagements": 1,
      "likes": 958
    }
  },
  {
    "id": "recrJLEE9zEJARTcI",
    "createdTime": "2024-08-08T18:39:19.000Z",
    "fields": {
      "Date (GMT)": "2024-08-08 16:46:58",
      "Job Link": "https://dashboard.browse.ai/teams/personal/robots/6b1f28ae-4557-4569-a58b-60e919d89150/history/cc9c4f41-0fb0-4ba7-baf0-577786d63544",
      "Origin URL": "https://taplio.com/lookup/codiesanchez",
      "Profile Links Limit": 100,
      "LinkedIn Posts Limit": 100,
      "followers": 283,
      "sd": 20,
      "engagements": 64,
      "likes": 54
    }
  },
  {
    "id": "recrsJorYVE3Tl1gW",
    "createdTime": "2024-08-08T18:39:19.000Z",
    "fields": {
      "Date (GMT)": "2024-08-08 17:01:18",
      "Job Link": "https://dashboard.browse.ai/teams/personal/robots/6b1f28ae-4557-4569-a58b-60e919d89150/history/dee929b1-794f-44b9-8bad-28ddf37d14a1",
      "Origin URL": "https://taplio.com/lookup/collincadmus",
      "Profile Links Limit": 100,
      "LinkedIn Posts Limit": 100,
      "followers": 85,
      "sd": 6,
      "engagements": 3,
      "likes": 3
    }
  },
  {
    "id": "rectDWWRYwKyy1stU",
    "createdTime": "2024-08-08T18:39:19.000Z",
    "fields": {
      "Date (GMT)": "2024-08-08 16:38:06",
      "Job Link": "https://dashboard.browse.ai/teams/personal/robots/6b1f28ae-4557-4569-a58b-60e919d89150/history/8766308b-edbc-43f8-a55e-9694df975ce6",
      "Origin URL": "https://taplio.com/lookup/dipl-ing-lars-behrendt",
      "Profile Links Limit": 100,
      "LinkedIn Posts Limit": 100,
      "followers": 263,
      "sd": 20,
      "engagements": 118,
      "likes": 105
    }
  },
  {
    "id": "rectet0Ncy0Eif2cL",
    "createdTime": "2024-08-08T18:39:19.000Z",
    "fields": {
      "Date (GMT)": "2024-08-08 16:56:25",
      "Job Link": "https://dashboard.browse.ai/teams/personal/robots/6b1f28ae-4557-4569-a58b-60e919d89150/history/af604345-23e5-465c-920e-ada8c1681cf4",
      "Origin URL": "https://taplio.com/lookup/jepsontaylor",
      "Profile Links Limit": 100,
      "LinkedIn Posts Limit": 100,
      "followers": 81,
      "sd": 12,
      "engagements": 640,
      "likes": 441
    }
  },
  {
    "id": "rectjWzSZjl2ykpAl",
    "createdTime": "2024-08-08T18:39:19.000Z",
    "fields": {
      "Date (GMT)": "2024-08-08 16:49:12",
      "Job Link": "https://dashboard.browse.ai/teams/personal/robots/6b1f28ae-4557-4569-a58b-60e919d89150/history/db95db4c-cf57-4607-a6eb-2d20ec194b0c",
      "Origin URL": "https://taplio.com/lookup/elfriedsamba",
      "Profile Links Limit": 100,
      "LinkedIn Posts Limit": 100,
      "followers": 202,
      "sd": 20,
      "engagements": 555,
      "likes": 508
    }
  },
  {
    "id": "rectpX3nmp9daazdZ",
    "createdTime": "2024-08-08T18:39:19.000Z",
    "fields": {
      "Date (GMT)": "2024-08-08 16:42:16",
      "Job Link": "https://dashboard.browse.ai/teams/personal/robots/6b1f28ae-4557-4569-a58b-60e919d89150/history/55159abf-c863-4571-8eb5-4b4e19e05133",
      "Origin URL": "https://taplio.com/lookup/briascoi",
      "Profile Links Limit": 100,
      "LinkedIn Posts Limit": 100,
      "followers": 151,
      "sd": 20,
      "engagements": 11,
      "likes": 9
    }
  },
  {
    "id": "recvoRhgiOf1WkMZl",
    "createdTime": "2024-08-08T18:39:19.000Z",
    "fields": {
      "Date (GMT)": "2024-08-08 16:39:42",
      "Job Link": "https://dashboard.browse.ai/teams/personal/robots/6b1f28ae-4557-4569-a58b-60e919d89150/history/0cbb77b3-e99c-4691-baec-76895f67945b",
      "Origin URL": "https://taplio.com/lookup/robdance",
      "Profile Links Limit": 100,
      "LinkedIn Posts Limit": 100,
      "followers": 119,
      "sd": 20,
      "engagements": 381,
      "likes": 326
    }
  },
  {
    "id": "recwUqD7ECL0GjHao",
    "createdTime": "2024-08-08T18:39:19.000Z",
    "fields": {
      "Date (GMT)": "2024-08-08 17:00:48",
      "Job Link": "https://dashboard.browse.ai/teams/personal/robots/6b1f28ae-4557-4569-a58b-60e919d89150/history/e110a6ae-f664-4a0f-a016-413f3aad923f",
      "Origin URL": "https://taplio.com/lookup/sahilmansuri",
      "Profile Links Limit": 100,
      "LinkedIn Posts Limit": 100,
      "followers": 74,
      "sd": 1,
      "engagements": 223,
      "likes": 203
    }
  },
  {
    "id": "recxWQ0pBvuIXdl7o",
    "createdTime": "2024-08-08T18:39:19.000Z",
    "fields": {
      "Date (GMT)": "2024-08-08 16:41:23",
      "Job Link": "https://dashboard.browse.ai/teams/personal/robots/6b1f28ae-4557-4569-a58b-60e919d89150/history/dbb35a72-40c9-402b-b7a4-7b78f95ec381",
      "Origin URL": "https://taplio.com/lookup/benmeer",
      "Profile Links Limit": 100,
      "LinkedIn Posts Limit": 100,
      "followers": 658,
      "sd": 20,
      "engagements": 233,
      "likes": 197
    }
  },
  {
    "id": "recxlNOwGjSbKOU7E",
    "createdTime": "2024-08-08T18:39:19.000Z",
    "fields": {
      "Date (GMT)": "2024-08-08 16:56:30",
      "Job Link": "https://dashboard.browse.ai/teams/personal/robots/6b1f28ae-4557-4569-a58b-60e919d89150/history/6070d312-f10c-4774-9c65-da140bbe32df",
      "Origin URL": "https://taplio.com/lookup/leon-gordon",
      "Profile Links Limit": 100,
      "LinkedIn Posts Limit": 100,
      "followers": 65,
      "sd": 20,
      "engagements": 2,
      "likes": 1
    }
  },
  {
    "id": "recyhwURB93vXasF6",
    "createdTime": "2024-08-08T18:39:19.000Z",
    "fields": {
      "Date (GMT)": "2024-08-08 16:50:55",
      "Job Link": "https://dashboard.browse.ai/teams/personal/robots/6b1f28ae-4557-4569-a58b-60e919d89150/history/146c96cc-beab-4b07-b128-5c808d9072de",
      "Origin URL": "https://taplio.com/lookup/mita-mallick-2b165822",
      "Profile Links Limit": 100,
      "LinkedIn Posts Limit": 100,
      "followers": 167,
      "sd": 20,
      "engagements": 47,
      "likes": 40
    }
  },
  {
    "id": "recyscyedu6ThcF8I",
    "createdTime": "2024-08-08T18:39:19.000Z",
    "fields": {
      "Date (GMT)": "2024-08-08 16:49:46",
      "Job Link": "https://dashboard.browse.ai/teams/personal/robots/6b1f28ae-4557-4569-a58b-60e919d89150/history/f1389993-eea3-406b-b439-0e8a62aa94c2",
      "Origin URL": "https://taplio.com/lookup/melissa-grabiner",
      "Profile Links Limit": 100,
      "LinkedIn Posts Limit": 100,
      "followers": 345,
      "sd": 20,
      "engagements": 91,
      "likes": 80
    }
  },
  {
    "id": "reczQw6ae08VruDVb",
    "createdTime": "2024-08-08T18:39:19.000Z",
    "fields": {
      "Date (GMT)": "2024-08-08 16:44:48",
      "Job Link": "https://dashboard.browse.ai/teams/personal/robots/6b1f28ae-4557-4569-a58b-60e919d89150/history/4dcdff4f-ce24-44d6-8cb0-ab4a207414b9",
      "Origin URL": "https://taplio.com/lookup/jwmba",
      "Profile Links Limit": 100,
      "LinkedIn Posts Limit": 100,
      "followers": 290,
      "sd": 20,
      "engagements": 175,
      "likes": 146
    }
  },
  {
    "id": "reczaEbFLxUNDkyF0",
    "createdTime": "2024-08-08T18:39:19.000Z",
    "fields": {
      "Date (GMT)": "2024-08-08 16:44:40",
      "Job Link": "https://dashboard.browse.ai/teams/personal/robots/6b1f28ae-4557-4569-a58b-60e919d89150/history/06fecf0c-b37d-45bd-b570-9fef37c890dc",
      "Origin URL": "https://taplio.com/lookup/hlarsson",
      "Profile Links Limit": 100,
      "LinkedIn Posts Limit": 100,
      "followers": 163,
      "sd": 20,
      "engagements": 68,
      "likes": 56
    }
  }
]